md_img_uri/__init__.py
md_img_uri/cli.py
md_img_uri/py.typed
md_img_uri-0.1.0.dist-info/WHEEL
md_img_uri-0.1.0.dist-info/entry_points.txt
md_img_uri-0.1.0.dist-info/METADATA
md_img_uri-0.1.0.dist-info/RECORD
