Metadata-Version: 2.3
Name: md-img-uri
Version: 0.1.0
Summary: Embed images into Markdown as data URIs
Keywords: markdown,image,data-uri,base64,svg,embedding
Author: Ralph Schmieder
Author-email: Ralph Schmieder <rschmied@cisco.com>
License: MIT
Classifier: Development Status :: 4 - Beta
Classifier: Environment :: Console
Classifier: Intended Audience :: Developers
Classifier: License :: OSI Approved :: MIT License
Classifier: Operating System :: OS Independent
Classifier: Programming Language :: Python :: 3
Classifier: Programming Language :: Python :: 3.12
Classifier: Topic :: Text Processing :: Markup :: Markdown
Classifier: Topic :: Utilities
Requires-Dist: pillow>=10.0.0
Requires-Dist: pytest>=7.0.0 ; extra == 'dev'
Requires-Python: >=3.12
Project-URL: Issues, https://github.com/rschmied/md-img-uri/issues
Project-URL: Repository, https://github.com/rschmied/md-img-uri
Provides-Extra: dev
